{
  "dimension": "talent",
  "metric_key": "ai_papers_by_country_12m",
  "description": "AI-related research papers (Artificial Intelligence, Machine Learning, NLP, Computer Vision concepts) published in the last 365 days, counted by country of author institution. Source: OpenAlex. A proxy for research output, not a complete measure of talent or capability.",
  "fetched_at": "2026-03-20T03:38:19.359678+00:00",
  "window_days": 365,
  "source": {
    "name": "OpenAlex API",
    "url": "https://api.openalex.org/works",
    "note": "group_by=authorships.institutions.country_code on AI/ML/NLP/CV concepts. Papers with authors from multiple countries are counted in each country. OpenAlex pre-computes institutional affiliations from publisher metadata."
  },
  "summary": {
    "US": 0,
    "China": 0,
    "Other": 998442,
    "Unknown": 0,
    "total_papers": 1463105,
    "total_attributed": 998442
  },
  "top_countries": [
    {
      "country_code": "https://openalex.org/countries/CN",
      "count": 226466
    },
    {
      "country_code": "https://openalex.org/countries/US",
      "count": 126666
    },
    {
      "country_code": "https://openalex.org/countries/JP",
      "count": 79018
    },
    {
      "country_code": "https://openalex.org/countries/IN",
      "count": 74233
    },
    {
      "country_code": "https://openalex.org/countries/GB",
      "count": 40922
    },
    {
      "country_code": "https://openalex.org/countries/DE",
      "count": 31750
    },
    {
      "country_code": "https://openalex.org/countries/ID",
      "count": 26756
    },
    {
      "country_code": "https://openalex.org/countries/IT",
      "count": 20287
    },
    {
      "country_code": "https://openalex.org/countries/CA",
      "count": 20248
    },
    {
      "country_code": "https://openalex.org/countries/FR",
      "count": 19546
    }
  ],
  "papers": [
    {
      "id": "https://openalex.org/W3015352082",
      "title": "The construct of institutional distance through the lens of diverse institutional perspectives: Review, analysis, and future directions.",
      "authors": [
        "Tatiana Kostova",
        "Sjoerd Beugelsdijk",
        "R. Scott"
      ],
      "countries": [],
      "primary_country": "Unknown",
      "published": "2050-01-01",
      "source": "openalex"
    },
    {
      "id": "https://openalex.org/W7125433533",
      "title": "Role-Based Task Distribution in YAWL",
      "authors": [
        "Andreas V. Hense"
      ],
      "countries": [
        "DE"
      ],
      "primary_country": "Other",
      "published": "2046-02-26",
      "source": "openalex"
    },
    {
      "id": "https://openalex.org/W7105905842",
      "title": "Supplementary data: “Is metaphony (and sound change) sensitive to grammatical category? The case of verbs in the dialects of the Lausberg area\" (Phonology)",
      "authors": [
        "Greca, Pia",
        "Harrington, Jonathan"
      ],
      "countries": [],
      "primary_country": "Unknown",
      "published": "2041-01-01",
      "source": "openalex"
    },
    {
      "id": "https://openalex.org/W7114991344",
      "title": "Consciousness, Self-Consciousness, and the Nested Vacuum Structure: A Transdisciplinary Model Integrating Biological Coherence (Θ), Mind (Ψ), Culture (Logos), and the Meta Vacuum (𝒱)",
      "authors": [
        "Schmieke, Marcus"
      ],
      "countries": [],
      "primary_country": "Unknown",
      "published": "2035-12-12",
      "source": "openalex"
    },
    {
      "id": "https://openalex.org/W7115176317",
      "title": "Consciousness, Self-Consciousness, and the Nested Vacuum Structure: A Transdisciplinary Model Integrating Biological Coherence (Θ), Mind (Ψ), Culture (Logos), and the Meta Vacuum (𝒱)",
      "authors": [
        "Schmieke, Marcus"
      ],
      "countries": [],
      "primary_country": "Unknown",
      "published": "2035-12-12",
      "source": "openalex"
    },
    {
      "id": "https://openalex.org/W7126002787",
      "title": "Visualizing grammars across space and time (ViGramm) (resp. Diego Pescarini)",
      "authors": [
        "Stella Retali-Medori"
      ],
      "countries": [
        "FR"
      ],
      "primary_country": "Other",
      "published": "2031-06-01",
      "source": "openalex"
    },
    {
      "id": "https://openalex.org/W7128405138",
      "title": "Essays on Financial Machine Learning: Nonlinearity, Predictability and Data-Theory Integration",
      "authors": [
        "Yinuo Wang"
      ],
      "countries": [],
      "primary_country": "Unknown",
      "published": "2031-01-01",
      "source": "openalex"
    },
    {
      "id": "https://openalex.org/W7134252063",
      "title": "Depth of Processing, learner aptitude, and the acquisition of L2 English grammatical structures",
      "authors": [
        "Shweta Nigam"
      ],
      "countries": [],
      "primary_country": "Unknown",
      "published": "2031-01-01",
      "source": "openalex"
    },
    {
      "id": "https://openalex.org/W7128533681",
      "title": "Mathematical modelling of epidemics, evolution and social interaction",
      "authors": [
        "Wajid Ali"
      ],
      "countries": [],
      "primary_country": "Unknown",
      "published": "2031-01-01",
      "source": "openalex"
    },
    {
      "id": "https://openalex.org/W7128488639",
      "title": "Comparative assessment of AGAMOUS function in the Brassicaceae",
      "authors": [
        "Jesse McCarthy"
      ],
      "countries": [],
      "primary_country": "Unknown",
      "published": "2031-01-01",
      "source": "openalex"
    },
    {
      "id": "https://openalex.org/W7128624139",
      "title": "Combating Data and Target Shifts in Visual Tasks",
      "authors": [
        "Zhaorui Tan"
      ],
      "countries": [],
      "primary_country": "Unknown",
      "published": "2031-01-01",
      "source": "openalex"
    },
    {
      "id": "https://openalex.org/W7128501788",
      "title": "APPLICATION OF MACHINE LEARNING FOR MASS CYTOMETRY DATA ANALYSIS OF CHRONIC LYMPHOCYTIC LEUKAEMIA",
      "authors": [
        "Muizdeen Raji"
      ],
      "countries": [],
      "primary_country": "Unknown",
      "published": "2031-01-01",
      "source": "openalex"
    },
    {
      "id": "https://openalex.org/W7106116102",
      "title": "PAGAD: Projective Adversarial Generator for Image Anomaly Detection",
      "authors": [
        "MohammadiRaouf, Saman",
        "Amirmazlaghani, Maryam"
      ],
      "countries": [
        "IR"
      ],
      "primary_country": "Other",
      "published": "2030-01-01",
      "source": "openalex"
    },
    {
      "id": "https://openalex.org/W7106142489",
      "title": "PAGAD: Projective Adversarial Generator for Image Anomaly Detection",
      "authors": [
        "MohammadiRaouf, Saman",
        "Amirmazlaghani, Maryam"
      ],
      "countries": [
        "IR"
      ],
      "primary_country": "Other",
      "published": "2030-01-01",
      "source": "openalex"
    },
    {
      "id": "https://openalex.org/W3194895376",
      "title": "Decision responsiveness and the legitimacy of public agencies data set",
      "authors": [
        "Ben Seyd"
      ],
      "countries": [],
      "primary_country": "Unknown",
      "published": "2030-01-01",
      "source": "openalex"
    }
  ],
  "methodology_note": "Paper counts are sourced from OpenAlex, which indexes most major academic publishers and preprint servers (including arXiv). Each paper is counted once for each country where at least one author has an identified institution. A paper with US and Chinese co-authors is counted in both US and China totals — the sum of country counts therefore exceeds the total paper count. Country classification relies on OpenAlex's institution-to-country mapping, which uses ISO 3166-1 alpha-2 country codes. Unknown = papers where no author has any identified institutional affiliation in OpenAlex. This metric measures output volume — it does not capture citation impact, researcher headcount, or research quality. Coverage may exclude some journals or publishers not indexed by OpenAlex. Chinese researchers may also publish to venues not well-indexed internationally."
}